shallowwater/__init__.py
shallowwater/diagnostics.py
shallowwater/dynamics.py
shallowwater/forcing.py
shallowwater/grid.py
shallowwater/initial.py
shallowwater/operators.py
shallowwater/operators_numba.py
shallowwater/params.py
shallowwater/runner.py
shallowwater/visualize.py
shallowwater-0.1.1.dist-info/licenses/LICENSE
shallowwater-0.1.1.dist-info/METADATA
shallowwater-0.1.1.dist-info/WHEEL
shallowwater-0.1.1.dist-info/top_level.txt
shallowwater-0.1.1.dist-info/RECORD
