Metadata-Version: 2.4
Name: shallowwater
Version: 0.1.1
Summary: Shallow-water model on a C-grid over a beta-plane (educational)
Author-email: Fabien Roquet <fabien.roquet@gu.se>
License: MIT
Project-URL: Homepage, https://github.com/fabien-roquet/shallowwater
Project-URL: Issues, https://github.com/fabien-roquet/shallowwater/issues
Requires-Python: >=3.9
License-File: LICENSE
Requires-Dist: numpy>=1.24
Requires-Dist: matplotlib>=3.8
Requires-Dist: pillow>=9.0
Requires-Dist: jupyter>=1.0
Provides-Extra: numba
Requires-Dist: numba>=0.59; extra == "numba"
Dynamic: license-file
